Metadata-Version: 1.1
Name: ngCGH
Version: 0.4.2
Summary: Pseudo-cgh of next-generation sequencing data
Home-page: http://github.com/seandavi/ngCGH
Author: Sean Davis
Author-email: sdavis2@mail.nih.gov
License: GPL-2
Platform: UNKNOWN
Classifier: Topic :: Scientific/Engineering :: Bio-Informatics
